[
  {
    "imgSrc": "https://www.lenovo.com/medias/GY40Y57708-01-500x400.png?context=bWFzdGVyfHJvb3R8MTE0NTYxfGltYWdlL3BuZ3xoMmEvaDg5LzExMDQ1MTIwNTA3OTM0LnBuZ3xlZDFkNmMyOTc3YTY5NzAxOWU0ZmM0NDZkMTAyZDQxNjdjNjUyZGUzNmZlNmRlNTc0MzVhM2I1YjBkOTE4M2I2",
    "imgAltTxt": "Gaming Keyboard",
    "heading": "Gaming Keyboard",
    "description": "For a better gaming experience, try to get a high-quality gaming keyboard, and you'll see the difference!",
    "topicTag": "Gamer"
  },
  {
    "imgSrc": "https://dlcdnwebimgs.asus.com/gain/45DB5297-607F-4F96-B318-65007AC3D5EE/w717/h525",
    "imgAltTxt": "Rog Phone",
    "heading": "Rog Phone",
    "description": "For a better gaming experience, try to get a high-quality gaming keyboard, and you'll see the difference!",
    "topicTag": "Gamer"
  },
  {
    "imgSrc": "https://www.readtosucceed.org/wp-content/uploads/2019/02/book-stack.png",
    "imgAltTxt": "Books",
    "heading": "Books",
    "description": "For a better gaming experience, try to get a high-quality gaming keyboard, and you'll see the difference!",
    "topicTag": "Education"
  },
  {
    "imgSrc": "https://thumbs.dreamstime.com/b/university-toronto-st-george-campus-architectural-architecture-building-old-tourism-stone-gothic-landmark-beautiful-downtown-161529545.jpg",
    "imgAltTxt": "University Life",
    "heading": "University Life",
    "description": "For a better gaming experience, try to get a high-quality gaming keyboard, and you'll see the difference!",
    "topicTag": "Education"
  },
  {
    "imgSrc": "https://www.roboticsbusinessreview.com/wp-content/uploads/2020/08/Moxie_Tech-200x400-1.png",
    "imgAltTxt": "Robot Hardware",
    "heading": "Robot Hardware",
    "description": "For a better gaming experience, try to get a high-quality gaming keyboard, and you'll see the difference!",
    "topicTag": "Technology"
  },
  {
    "imgSrc": "https://www.eweek.com/wp-content/uploads/2022/05/enterprise-AI.jpg",
    "imgAltTxt": "AI Teaching",
    "heading": "AI Teaching",
    "description": "For a better gaming experience, try to get a high-quality gaming keyboard, and you'll see the difference!",
    "topicTag": "Technology"
  },
  {
    "imgSrc": "https://udmc.com.ph/wp-content/uploads/2022/08/contact-us-doctor.png",
    "imgAltTxt": "Clinical Doctor",
    "heading": "Clinical Doctor",
    "description": "For a better gaming experience, try to get a high-quality gaming keyboard, and you'll see the difference!",
    "topicTag": "Medicine"
  },
  {
    "imgSrc": "https://cdni.iconscout.com/illustration/premium/thumb/psychology-consultant-4813653-4023754.png",
    "imgAltTxt": "Psychology",
    "heading": "Psychology",
    "description": "For a better gaming experience, try to get a high-quality gaming keyboard, and you'll see the difference!",
    "topicTag": "Medicine"
  },
  {
    "imgSrc": "https://cdn-icons-png.flaticon.com/512/857/857152.png",
    "imgAltTxt": "Productivity Working From Home",
    "heading": "Productivity Working From Home",
    "description": "For a better gaming experience, try to get a high-quality gaming keyboard, and you'll see the difference!",
    "topicTag": "Productivity"
  },
  {
    "imgSrc": "https://worktechnology.com.br/wp-content/uploads/2022/12/Sobre_nos_worktechnology.png",
    "imgAltTxt": "Burnout at Work",
    "heading": "Burnout at Work",
    "description": "For a better gaming experience, try to get a high-quality gaming keyboard, and you'll see the difference!",
    "topicTag": "Productivity"
  },
  {
    "imgSrc": "https://www.gawler.sa.gov.au/__data/assets/image/0013/220018/recycle_logo_copy_ac4eba44aae6d8d1cb55c57204e32505.gif",
    "imgAltTxt": "Benefits of Recycling",
    "heading": "Benefits of Recycling",
    "description": "For a better gaming experience, try to get a high-quality gaming keyboard, and you'll see the difference!",
    "topicTag": "Sustainability"
  },
  {
    "imgSrc": "https://easydrawingguides.com/wp-content/uploads/2017/06/How-to-Draw-a-Cartoon-Forest-20.png",
    "imgAltTxt": "The Importance of Trees in Our Lives",
    "heading": "The Importance of Trees in Our Lives",
    "description": "For a better gaming experience, try to get a high-quality gaming keyboard, and you'll see the difference!",
    "topicTag": "Sustainability"
  }
]
